chitubox/__init__.py
chitubox/__main__.py
chitubox/network.py
chitubox/session.py
chitubox-0.1.5.dist-info/LICENSE
chitubox-0.1.5.dist-info/METADATA
chitubox-0.1.5.dist-info/WHEEL
chitubox-0.1.5.dist-info/entry_points.txt
chitubox-0.1.5.dist-info/top_level.txt
chitubox-0.1.5.dist-info/zip-safe
chitubox-0.1.5.dist-info/RECORD
