Metadata-Version: 2.1
Name: chitubox
Version: 0.1.5
Summary: Utility to manage networked ChiTuBox based LCD Resin printers
Home-page: https://github.com/ezrec/python-chitubox
Author: Jason S. McMullan
Author-email: jason.mcmullan@gmail.com
License: UNKNOWN
Platform: UNKNOWN
Classifier: Programming Language :: Python :: 3
Classifier: License :: OSI Approved :: MIT License
Classifier: Operating System :: OS Independent
Requires-Python: >=3.5
